constrNMPy-0.1.dist-info/top_level.txt
constrNMPy-0.1.dist-info/RECORD
constrNMPy-0.1.dist-info/pbr.json
constrNMPy-0.1.dist-info/METADATA
constrNMPy-0.1.dist-info/metadata.json
constrNMPy-0.1.dist-info/WHEEL
constrNMPy-0.1.dist-info/DESCRIPTION.rst
constrNMPy/constrNMPy.py
constrNMPy/__init__.py
constrNMPy/test_funcs.py
