Metadata-Version: 2.0
Name: constrNMPy
Version: 0.1
Summary: A Python package for constrained Nelder-Mead optimization.
Home-page: https://github.com/alexblaessle/constNMPy/
Author: Alexander Blaessle
Author-email: alexander.blaessle@gmail.com
License: GNU GPL v3
Keywords: Optimization Nelder-Mead Constrained
Platform: UNKNOWN
Classifier: Development Status :: 4 - Beta
Classifier: Intended Audience :: Science/Research
Classifier: Topic :: Scientific/Engineering
Classifier: License :: OSI Approved :: GNU General Public License v3 (GPLv3)
Classifier: Programming Language :: Python :: 2.7
Classifier: Programming Language :: Python :: 3
Classifier: Programming Language :: Python :: 3.2
Classifier: Programming Language :: Python :: 3.3
Classifier: Programming Language :: Python :: 3.4
Requires-Dist: numpy
Requires-Dist: scipy
